sendmail.py
python_sendmail-0.3.5.dist-info/licenses/LICENSE
tests/__init__.py
tests/test1.py
python_sendmail-0.3.5.dist-info/METADATA
python_sendmail-0.3.5.dist-info/WHEEL
python_sendmail-0.3.5.dist-info/entry_points.txt
python_sendmail-0.3.5.dist-info/top_level.txt
python_sendmail-0.3.5.dist-info/RECORD
