Metadata-Version: 2.4
Name: python-sendmail
Version: 0.3.5
Summary: Sendmail client. send mail via stmp server.
Author: rRR0VrFP
Maintainer: rRR0VrFP
License: MIT
Keywords: python-sendmail,pysendmail,sendmail,pysendeml,sendeml,mail
Classifier: Development Status :: 5 - Production/Stable
Classifier: Intended Audience :: Developers
Classifier: Topic :: Software Development :: Libraries :: Python Modules
Classifier: License :: OSI Approved :: MIT License
Classifier: Programming Language :: Python :: 3
Classifier: Programming Language :: Python :: 3 :: Only
Requires: click
License-File: LICENSE
Requires-Dist: click
Dynamic: author
Dynamic: classifier
Dynamic: description
Dynamic: description-content-type
Dynamic: keywords
Dynamic: license
Dynamic: license-file
Dynamic: maintainer
Dynamic: requires
Dynamic: requires-dist
Dynamic: summary
